forge/api.py
forge/db.py
forge/model.py
forge/gen/crud.py
forge/gen/fn.py
forge/gen/metadata.py
forge/utils/__init__.py
forge/utils/sql_types.py
crud_forge-0.3.1.dist-info/LICENSE
crud_forge-0.3.1.dist-info/METADATA
crud_forge-0.3.1.dist-info/WHEEL
crud_forge-0.3.1.dist-info/top_level.txt
crud_forge-0.3.1.dist-info/RECORD
