Metadata-Version: 2.1
Name: crud-forge
Version: 0.3.1
Summary: A package for generating FastAPI CRUD operations and routes
Home-page: https://github.com/Yrrrrrf/crud-forge
Author: Yrrrrrf
Author-email: Yrrrrrf <fernandorezacampos@gmail.com>
License: MIT
Project-URL: Homepage, https://github.com/Yrrrrrf/crud-forge
Project-URL: Repository, https://github.com/Yrrrrrf/crud-forge
Classifier: Development Status :: 3 - Alpha
Classifier: Intended Audience :: Developers
Classifier: Programming Language :: Python :: 3.10
Classifier: Programming Language :: Python :: 3.11
Classifier: Programming Language :: Python :: 3.12
Requires-Python: >=3.10
License-File: LICENSE
Requires-Dist: fastapi>=0.111.0
Requires-Dist: sqlalchemy>=2.0.30
Requires-Dist: pydantic>=2.7.1
Requires-Dist: psycopg2>=2.9.3
Provides-Extra: dev
Requires-Dist: pytest<7.0.0,>=6.2.5; extra == "dev"
Requires-Dist: black<22.0.0,>=21.9b0; extra == "dev"
Requires-Dist: isort<6.0.0,>=5.9.3; extra == "dev"
Requires-Dist: mypy<1.0,>=0.910; extra == "dev"
